alibabacloud_cas20200407/__init__.py
alibabacloud_cas20200407/client.py
alibabacloud_cas20200407/models/__init__.py
alibabacloud_cas20200407/models/_apply_certificate_request.py
alibabacloud_cas20200407/models/_apply_certificate_response.py
alibabacloud_cas20200407/models/_apply_certificate_response_body.py
alibabacloud_cas20200407/models/_cancel_certificate_for_package_request_request.py
alibabacloud_cas20200407/models/_cancel_certificate_for_package_request_response.py
alibabacloud_cas20200407/models/_cancel_certificate_for_package_request_response_body.py
alibabacloud_cas20200407/models/_cancel_order_request_request.py
alibabacloud_cas20200407/models/_cancel_order_request_response.py
alibabacloud_cas20200407/models/_cancel_order_request_response_body.py
alibabacloud_cas20200407/models/_cancel_pending_certificate_request.py
alibabacloud_cas20200407/models/_cancel_pending_certificate_response.py
alibabacloud_cas20200407/models/_cancel_pending_certificate_response_body.py
alibabacloud_cas20200407/models/_create_certificate_for_package_request_request.py
alibabacloud_cas20200407/models/_create_certificate_for_package_request_response.py
alibabacloud_cas20200407/models/_create_certificate_for_package_request_response_body.py
alibabacloud_cas20200407/models/_create_certificate_request_request.py
alibabacloud_cas20200407/models/_create_certificate_request_response.py
alibabacloud_cas20200407/models/_create_certificate_request_response_body.py
alibabacloud_cas20200407/models/_create_certificate_with_csr_request_request.py
alibabacloud_cas20200407/models/_create_certificate_with_csr_request_response.py
alibabacloud_cas20200407/models/_create_certificate_with_csr_request_response_body.py
alibabacloud_cas20200407/models/_create_csr_request.py
alibabacloud_cas20200407/models/_create_csr_response.py
alibabacloud_cas20200407/models/_create_csr_response_body.py
alibabacloud_cas20200407/models/_create_deployment_job_request.py
alibabacloud_cas20200407-3.1.0.dist-info/LICENSE
alibabacloud_cas20200407-3.1.0.dist-info/METADATA
alibabacloud_cas20200407-3.1.0.dist-info/WHEEL
alibabacloud_cas20200407-3.1.0.dist-info/top_level.txt
alibabacloud_cas20200407-3.1.0.dist-info/RECORD
